prompton/__init__.py
prompton/client.py
prompton/core/__init__.py
prompton/core/api_error.py
prompton/core/datetime_utils.py
prompton/core/jsonable_encoder.py
prompton/core/remove_none_from_headers.py
prompton/errors/__init__.py
prompton/errors/bad_request_error.py
prompton/errors/conflict_error.py
prompton/errors/not_found_error.py
prompton/errors/unauthorized_error.py
prompton/errors/unprocessable_entity_error.py
prompton/resources/__init__.py
prompton/resources/authentication/__init__.py
prompton/resources/authentication/client.py
prompton/resources/feedbacks/__init__.py
prompton/resources/feedbacks/client.py
prompton/resources/inferences/__init__.py
prompton/resources/inferences/client.py
prompton/resources/orgs/__init__.py
prompton/resources/orgs/client.py
prompton/resources/prompt_versions/__init__.py
prompton/resources/prompt_versions/client.py
prompton/resources/prompts/__init__.py
prompton/resources/prompts/client.py
prompton/resources/server_status/__init__.py
prompton/resources/server_status/client.py
prompton/resources/users/__init__.py
prompton/resources/users/client.py
prompton/types/__init__.py
prompton/types/api_status_response.py
prompton/types/body_get_access_token_extended_token_post.py
prompton/types/chat_gpt_chat_completition_config.py
prompton/types/chat_gpt_chat_completition_config_stop.py
prompton/types/chat_gpt_chat_completition_request.py
prompton/types/chat_gpt_chat_completition_request_stop.py
prompton/types/chat_gpt_chat_completition_response.py
prompton/types/chat_gpt_completition_choice.py
prompton/types/chat_gpt_message.py
prompton/types/chat_gpt_role.py
prompton/types/chat_gpt_token_usage.py
prompton/types/db_status.py
prompton/types/default_post_response.py
prompton/types/feedback_read.py
prompton/types/http_validation_error.py
prompton/types/inference_create_by_prompt_id.py
prompton/types/inference_create_by_prompt_version_id.py
prompton/types/inference_error.py
prompton/types/inference_post_response.py
prompton-0.0.10.dist-info/METADATA
prompton-0.0.10.dist-info/WHEEL
prompton-0.0.10.dist-info/RECORD
